os11/Slip.py
os11/Slip1.py
os11/Slip10.py
os11/Slip11.py
os11/Slip12.py
os11/Slip13.py
os11/Slip14.py
os11/Slip15.py
os11/Slip16.py
os11/Slip18.py
os11/Slip19.py
os11/Slip2.py
os11/Slip20.py
os11/Slip21.py
os11/Slip22.py
os11/Slip23.py
os11/Slip24.py
os11/Slip25.py
os11/Slip26.py
os11/Slip27.py
os11/Slip28.py
os11/Slip29.py
os11/Slip3.py
os11/Slip30.py
os11/Slip4.py
os11/Slip5.py
os11/Slip6.py
os11/Slip7.py
os11/Slip8.py
os11/Slip9.py
os11/__init__.py
os11-0.0.3.dist-info/LICENSE.txt
os11-0.0.3.dist-info/METADATA
os11-0.0.3.dist-info/WHEEL
os11-0.0.3.dist-info/top_level.txt
os11-0.0.3.dist-info/RECORD
